mxersion/__init__.py
mxersion/hello.py
mxersion-0.3.dist-info/LICENSE
mxersion-0.3.dist-info/METADATA
mxersion-0.3.dist-info/WHEEL
mxersion-0.3.dist-info/top_level.txt
mxersion-0.3.dist-info/RECORD
