Metadata-Version: 2.1
Name: mxersion
Version: 0.3
Summary: mxersion is an package to interact with mxersion s api and features
Home-page: https://github.com/your_username/your_package_name
Author: Mxytyu
Author-email: mersion@gmail.com
License: MIT
License-File: LICENSE
